nrt_collections_utils/__init__.py
nrt_collections_utils/collections_utils.py
nrt_collections_utils/dict_utils.py
nrt_collections_utils/list_utils.py
nrt_collections_utils-1.0.5.dist-info/METADATA
nrt_collections_utils-1.0.5.dist-info/WHEEL
nrt_collections_utils-1.0.5.dist-info/licenses/LICENSE
nrt_collections_utils-1.0.5.dist-info/RECORD
