Metadata-Version: 2.3
Name: nrt-collections-utils
Version: 1.0.5
Dynamic: Requires-Dist
Summary: Collections utilities in Python
Project-URL: Homepage, https://github.com/etuzon/python-nrt-collections-utils
Project-URL: Bug Tracker, https://github.com/etuzon/python-nrt-collections-utils/issues
Project-URL: documentation, https://github.com/etuzon/python-nrt-collections-utils/wiki
Author-email: Eyal Tuzon <eyal.tuzon.dev@gmail.com>
Keywords: collection,collections,collections-utilities,collections-utils,list,list-utilities,list-utils,nrt,nrt-collections-utilities,nrt-collections-utils,nrt-list-utilities,nrt-list-utils,nrt-utils,python,python-3,python3,tool,tools,util,utilities,utils
Classifier: Development Status :: 5 - Production/Stable
Classifier: Operating System :: OS Independent
Classifier: Programming Language :: Python :: 3
Classifier: Programming Language :: Python :: 3.8
Classifier: Programming Language :: Python :: 3.9
Classifier: Programming Language :: Python :: 3.10
Classifier: Programming Language :: Python :: 3.11
Classifier: Programming Language :: Python :: 3.12
Classifier: Programming Language :: Python :: 3.13
Classifier: Programming Language :: Python :: 3.14
Requires-Python: >=3.8
